{
  "typee": "fixed",
  "capacity": 16,
  "partitions": 4,
  "alg": "",
  "processes": [
    {
      "event": "IN",
      "pid": "A",
      "psize": 3
    },
    {
      "event": "IN",
      "pid": "B",
      "psize": 2
    },
    {
      "event": "IN",
      "pid": "C",
      "psize": 1
    },
    {
      "event": "OUT",
      "pid": "B"
    },
    {
      "event": "IN",
      "pid": "D",
      "psize": 4
    },
    {
      "event": "OUT",
      "pid": "A"
    },
    {
      "event": "OUT",
      "pid": "C"
    },
    {
      "event": "OUT",
      "pid": "D"
    }
  ]
}
